rt_server_client/__init__.py
rt_server_client/ToolBox/__init__.py
rt_server_client/ToolBox/base/__init__.py
rt_server_client/ToolBox/colors/__init__.py
rt_server_client/ToolBox/dell/__init__.py
rt_server_client/ToolBox/init/__init__.py
rt_server_client/ToolBox/net/__init__.py
rt_server_client/sysinfo/__init__.py
rt_server_client-3.1.0.data/scripts/comment-edit
rt_server_client-3.1.0.data/scripts/get-bios-ident
rt_server_client-3.1.0.data/scripts/system-info
rt_server_client-3.1.0.dist-info/LICENSE
rt_server_client-3.1.0.dist-info/METADATA
rt_server_client-3.1.0.dist-info/WHEEL
rt_server_client-3.1.0.dist-info/top_level.txt
rt_server_client-3.1.0.dist-info/RECORD
