Metadata-Version: 2.1
Name: rt-server-client
Version: 3.1.0
Summary: Racktables Server client for automation
Home-page: https://github.com/rvojcik/rt-server-client
Author: Robert Vojcik
Author-email: robert@vojcik.net
License: GPLv3
Keywords: rtapi,racktables,racktables automation,automation,server,racktables-client,rt-server-client,rt-client
Platform: UNKNOWN
Classifier: License :: OSI Approved :: GNU General Public License v3 (GPLv3)
Classifier: Operating System :: POSIX
Classifier: Operating System :: Unix
Classifier: Programming Language :: Python
Classifier: Programming Language :: Python :: 3
Classifier: Programming Language :: Python :: 3 :: Only
Classifier: Topic :: Documentation
Classifier: Topic :: System :: Systems Administration
Classifier: Topic :: Utilities
Classifier: Topic :: Database
Requires-Dist: ipaddr
Requires-Dist: racktables-api (>=0.2.7)
